<?xml version="1.0" encoding="utf-8" ?>
<dwsync>
<file name="apc.php" server="pavimpresostalavera.es" local="131738174906844707" remote="131758014000000000" Dst="2" />
<file name="database.php" server="pavimpresostalavera.es" local="131738174904583516" remote="131758014000000000" Dst="2" />
<file name="eaccelerator.php" server="pavimpresostalavera.es" local="131738174904583516" remote="131758014000000000" Dst="2" />
<file name="index.html" server="pavimpresostalavera.es" local="131738174903019746" remote="131758014000000000" Dst="2" />
<file name="memcache.php" server="pavimpresostalavera.es" local="131738174902863946" remote="131758014000000000" Dst="2" />
<file name="memcached.php" server="pavimpresostalavera.es" local="131738174901613468" remote="131758014000000000" Dst="2" />
<file name="none.php" server="pavimpresostalavera.es" local="131738174901457227" remote="131758014000000000" Dst="2" />
<file name="wincache.php" server="pavimpresostalavera.es" local="131738174900352491" remote="131758014000000000" Dst="2" />
<file name="xcache.php" server="pavimpresostalavera.es" local="131738174900040844" remote="131758014000000000" Dst="2" />
</dwsync>