<?xml version="1.0" encoding="utf-8" ?>
<dwsync>
<file name="albanian.js" server="pavimpresostalavera.es" local="131738178276685467" remote="131758017000000000" Dst="2" />
<file name="arabic.js" server="pavimpresostalavera.es" local="131738178276375537" remote="131758017000000000" Dst="2" />
<file name="brazilian.js" server="pavimpresostalavera.es" local="131738178275355694" remote="131758017000000000" Dst="2" />
<file name="chinese.js" server="pavimpresostalavera.es" local="131738178273856516" remote="131758017000000000" Dst="2" />
<file name="czech.js" server="pavimpresostalavera.es" local="131738178273447332" remote="131758017000000000" Dst="2" />
<file name="catala.js" server="pavimpresostalavera.es" local="131738178274915772" remote="131758017000000000" Dst="2" />
<file name="english.js" server="pavimpresostalavera.es" local="131738178270206587" remote="131758017000000000" Dst="2" />
<file name="danish.js" server="pavimpresostalavera.es" local="131738178272029094" remote="131758017000000000" Dst="2" />
<file name="dutch.js" server="pavimpresostalavera.es" local="131738178271628833" remote="131758017000000000" Dst="2" />
<file name="estonian.js" server="pavimpresostalavera.es" local="131738178269956626" remote="131758017000000000" Dst="2" />
<file name="euskara.js" server="pavimpresostalavera.es" local="131738178268332224" remote="131758017000000000" Dst="2" />
<file name="finnish.js" server="pavimpresostalavera.es" local="131738178268142246" remote="131758017000000000" Dst="2" />
<file name="french.js" server="pavimpresostalavera.es" local="131738178266853629" remote="131758017000000000" Dst="2" />
<file name="galego.js" server="pavimpresostalavera.es" local="131738178266883632" remote="131758017000000000" Dst="2" />
<file name="german.js" server="pavimpresostalavera.es" local="131738178265393316" remote="131758017000000000" Dst="2" />
<file name="hungarian.js" server="pavimpresostalavera.es" local="131738178263593202" remote="131758017000000000" Dst="2" />
<file name="icelandic.js" server="pavimpresostalavera.es" local="131738178263403228" remote="131758017000000000" Dst="2" />
<file name="greek.js" server="pavimpresostalavera.es" local="131738178265423277" remote="131758017000000000" Dst="2" />
<file name="index.html" server="pavimpresostalavera.es" local="131738178261752142" remote="130298904000000000" Dst="2" />
<file name="indonesian.js" server="pavimpresostalavera.es" local="131738178261772067" remote="131758017000000000" Dst="2" />
<file name="italian.js" server="pavimpresostalavera.es" local="131738178259972359" remote="131758017000000000" Dst="2" />
<file name="macedonian.js" server="pavimpresostalavera.es" local="131738178259862372" remote="131758017000000000" Dst="2" />
<file name="norwegian.js" server="pavimpresostalavera.es" local="131738178258682567" remote="131758017000000000" Dst="2" />
<file name="polish.js" server="pavimpresostalavera.es" local="131738178256882607" remote="131758017000000000" Dst="2" />
<file name="portuguese.js" server="pavimpresostalavera.es" local="131738178254913610" remote="131758017000000000" Dst="2" />
<file name="romanian.js" server="pavimpresostalavera.es" local="131738178253664238" remote="131758017000000000" Dst="2" />
<file name="russian.js" server="pavimpresostalavera.es" local="131738178242338097" remote="131758017000000000" Dst="2" />
<file name="slovak.js" server="pavimpresostalavera.es" local="131738178240555660" remote="131758017000000000" Dst="2" />
<file name="slovenian.js" server="pavimpresostalavera.es" local="131738178238148360" remote="131758017000000000" Dst="2" />
<file name="spanish.js" server="pavimpresostalavera.es" local="131738178236622870" remote="131758017000000000" Dst="2" />
<file name="swedish.js" server="pavimpresostalavera.es" local="131738178235170108" remote="131758017000000000" Dst="2" />
<file name="thai.js" server="pavimpresostalavera.es" local="131738178233585353" remote="131758017000000000" Dst="2" />
<file name="turkish.js" server="pavimpresostalavera.es" local="131738178232095456" remote="131758017000000000" Dst="2" />
<file name="ukrainian.js" server="pavimpresostalavera.es" local="131738178230063255" remote="131758017000000000" Dst="2" />
<file name="vietnamese.js" server="pavimpresostalavera.es" local="131738178258332622" remote="131758017000000000" Dst="2" />
</dwsync>