<?xml version="1.0" encoding="utf-8" ?>
<dwsync>
<file name="base.php" server="pavimpresostalavera.es" local="131738174525231701" remote="131758013400000000" Dst="2" />
<file name="application.php" server="pavimpresostalavera.es" local="131738174527321149" remote="131758013400000000" Dst="2" />
<file name="categories.php" server="pavimpresostalavera.es" local="131738174524852013" remote="131758013400000000" Dst="2" />
<file name="cli.php" server="pavimpresostalavera.es" local="131738174523553350" remote="131758013400000000" Dst="2" />
<file name="daemon.php" server="pavimpresostalavera.es" local="131738174522613002" remote="131758013400000000" Dst="2" />
<file name="helper.php" server="pavimpresostalavera.es" local="131738174521909720" remote="131758013400000000" Dst="2" />
<file name="index.html" server="pavimpresostalavera.es" local="131738174520201673" remote="131758013400000000" Dst="2" />
<file name="input.php" server="pavimpresostalavera.es" local="131738174519741737" remote="131758013400000000" Dst="2" />
<file name="menu.php" server="pavimpresostalavera.es" local="131738174518542003" remote="131758013400000000" Dst="2" />
<file name="pathway.php" server="pavimpresostalavera.es" local="131738174518321974" remote="131758013400000000" Dst="2" />
<file name="router.php" server="pavimpresostalavera.es" local="131738174517140993" remote="131758013400000000" Dst="2" />
<file name="web.php" server="pavimpresostalavera.es" local="131738174516911051" remote="131758013400000000" Dst="2" />
</dwsync>