<?xml version="1.0" encoding="utf-8" ?>
<dwsync>
<file name="adapter.php" server="pavimpresostalavera.es" local="131738171680358824" remote="131758008600000000" Dst="2" />
<file name="helper.php" server="pavimpresostalavera.es" local="131738171679728940" remote="131758008600000000" Dst="2" />
<file name="index.html" server="pavimpresostalavera.es" local="131738171678097847" remote="131758008600000000" Dst="2" />
<file name="indexer.php" server="pavimpresostalavera.es" local="131738171678607749" remote="131758008600000000" Dst="2" />
<file name="parser.php" server="pavimpresostalavera.es" local="131738171676231923" remote="131758008600000000" Dst="2" />
<file name="query.php" server="pavimpresostalavera.es" local="131738171676451653" remote="131758008600000000" Dst="2" />
<file name="result.php" server="pavimpresostalavera.es" local="131738171674430536" remote="131758008600000000" Dst="2" />
<file name="stemmer.php" server="pavimpresostalavera.es" local="131738171674110582" remote="131758008600000000" Dst="2" />
<file name="taxonomy.php" server="pavimpresostalavera.es" local="131738171673119418" remote="131758008600000000" Dst="2" />
<file name="token.php" server="pavimpresostalavera.es" local="131738171672546709" remote="131758008600000000" Dst="2" />
</dwsync>